qolmat/__init__.py
qolmat/_version.py
qolmat/analysis/__init__.py
qolmat/analysis/holes_characterization.py
qolmat/benchmark/__init__.py
qolmat/benchmark/comparator.py
qolmat/benchmark/hyperparameters.py
qolmat/benchmark/metrics.py
qolmat/benchmark/missing_patterns.py
qolmat/data/beijing.csv
qolmat/data/conductors.csv
qolmat/imputations/__init__.py
qolmat/imputations/em_sampler.py
qolmat/imputations/imputers.py
qolmat/imputations/imputers_pytorch.py
qolmat/imputations/preprocessing.py
qolmat/imputations/softimpute.py
qolmat/imputations/diffusions/__init__.py
qolmat/imputations/diffusions/base.py
qolmat/imputations/diffusions/ddpms.py
qolmat/imputations/rpca/__init__.py
qolmat/imputations/rpca/rpca.py
qolmat/imputations/rpca/rpca_noisy.py
qolmat/imputations/rpca/rpca_pcp.py
qolmat/imputations/rpca/rpca_utils.py
qolmat/utils/__init__.py
qolmat/utils/algebra.py
qolmat/utils/data.py
qolmat/utils/exceptions.py
qolmat/utils/input_check.py
qolmat/utils/plot.py
qolmat/utils/utils.py
qolmat-0.2.0.dist-info/METADATA
qolmat-0.2.0.dist-info/WHEEL
qolmat-0.2.0.dist-info/licenses/AUTHORS.rst
qolmat-0.2.0.dist-info/licenses/LICENSE
qolmat-0.2.0.dist-info/RECORD
