Metadata-Version: 2.4
Name: qolmat
Version: 0.2.0
Summary: A Python library for optimal data imputation.
Project-URL: Homepage, https://github.com/Quantmetry/qolmat
Project-URL: Documentation, https://qolmat.readthedocs.io/en/latest/
Project-URL: Repository, https://github.com/Quantmetry/qolmat
Project-URL: Bug Tracker, https://github.com/Quantmetry/qolmat/issues
Author-email: Julien ROUSSEL <julien.roussel@capgemini.com>, Anh Khoa NGO HO <anh-khoa.ngo-ho@capgemini.com>, Hong-Lan BOTTERMAN <hong-lan.botterman@capgemini.com>, Guillaume SAËS <guillaume.saes@capgemini.com>
License: BSD-3-Clause
License-File: AUTHORS.rst
License-File: LICENSE
Keywords: imputation
Classifier: Intended Audience :: Developers
Classifier: Intended Audience :: Science/Research
Classifier: License :: OSI Approved :: BSD License
Classifier: Operating System :: OS Independent
Classifier: Programming Language :: Python :: 3.9
Classifier: Programming Language :: Python :: 3.10
Classifier: Programming Language :: Python :: 3.11
Classifier: Programming Language :: Python :: 3.12
Classifier: Topic :: Scientific/Engineering
Classifier: Topic :: Software Development
Requires-Python: <3.13,>=3.9
Requires-Dist: category-encoders<3,>=2.6.3
Requires-Dist: dcor>=0.6
Requires-Dist: numba>=0.59
Requires-Dist: numpy>=1.24
Requires-Dist: pandas>=2.0.1
Requires-Dist: scikit-learn>=1.6
Requires-Dist: scikit-optimize>=0.9
Requires-Dist: scipy
Requires-Dist: statsmodels>=0.14.0
Requires-Dist: tqdm
Provides-Extra: checkers
Requires-Dist: bandit>=1.7.9; extra == 'checkers'
Requires-Dist: mypy==1.1.1; extra == 'checkers'
Requires-Dist: pytest-cov==4.0.0; extra == 'checkers'
Requires-Dist: pytest-mock==3.10.0; extra == 'checkers'
Requires-Dist: pytest==7.2.0; extra == 'checkers'
Requires-Dist: ruff>=0.6.3; extra == 'checkers'
Provides-Extra: ci
Requires-Dist: codecov>=2.1.13; extra == 'ci'
Provides-Extra: dev
Requires-Dist: bump2version==1.0.1; extra == 'dev'
Requires-Dist: ipykernel>=6.29.5; extra == 'dev'
Requires-Dist: jupyter==1.0.0; extra == 'dev'
Requires-Dist: jupyterlab==1.2.6; extra == 'dev'
Requires-Dist: jupytext==1.14.4; extra == 'dev'
Requires-Dist: matplotlib; extra == 'dev'
Requires-Dist: packaging==23.1; extra == 'dev'
Requires-Dist: pre-commit==2.21.0; extra == 'dev'
Requires-Dist: twine==3.7.1; extra == 'dev'
Requires-Dist: wheel==0.37.1; extra == 'dev'
Provides-Extra: docs
Requires-Dist: numpydoc==1.1.0; extra == 'docs'
Requires-Dist: sphinx-gallery>=0.15; extra == 'docs'
Requires-Dist: sphinx-markdown-tables; extra == 'docs'
Requires-Dist: sphinx-rtd-theme==1.0.0; extra == 'docs'
Requires-Dist: sphinx>=5.0; extra == 'docs'
Provides-Extra: torch
Requires-Dist: torch<2.5; extra == 'torch'
